{
  "kind": "collectionType",
  "collectionName": "recipes",
  "info": {
    "name": "recipe"
  },
  "options": {
    "increments": true,
    "timestamps": true,
    "draftAndPublish": true
  },
  "pluginOptions": {},
  "attributes": {
    "name": {
      "type": "string"
    },
    "ingredients": {
      "type": "richtext"
    },
    "instructions": {
      "type": "richtext"
    },
    "photo": {
      "model": "file",
      "via": "related",
      "allowedTypes": [
        "images",
        "files",
        "videos"
      ],
      "plugin": "upload",
      "required": false,
      "pluginOptions": {}
    },
    "category": {
      "via": "recipes",
      "model": "category"
    }
  }
}
